dags/extract_scimagojr.py
extract/__init__.py
extract/base_extractor.py
extract/scimagojr/__init__.py
extract/scimagojr/scimagojr_extractor.py
impactu_airflow-0.1.0.dist-info/licenses/LICENSE
impactu_airflow-0.1.0.dist-info/METADATA
impactu_airflow-0.1.0.dist-info/WHEEL
impactu_airflow-0.1.0.dist-info/top_level.txt
impactu_airflow-0.1.0.dist-info/RECORD
