Metadata-Version: 2.4
Name: impactu_airflow
Version: 0.1.0
Summary: Apache Airflow DAGs and ETL processes for ImpactU
Author-email: Colav <grupocolav@udea.edu.co>
License: BSD-2-Clause
Classifier: Programming Language :: Python :: 3
Classifier: License :: OSI Approved :: BSD License
Classifier: Operating System :: OS Independent
Classifier: Framework :: Apache Airflow
Requires-Python: >=3.12
License-File: LICENSE
Requires-Dist: apache-airflow-providers-mongo>=5.3.0
Requires-Dist: pymongo>=4.15.5
Requires-Dist: pandas>=2.1.4
Requires-Dist: requests>=2.32.5
Dynamic: license-file
